pyyacp/__init__.py
pyyacp/cli.py
pyyacp/config.py
pyyacp/config.yaml
pyyacp/datatable.py
pyyacp/table_structure_helper.py
pyyacp/timer.py
pyyacp/profiler/__init__.py
pyyacp/profiler/colum_pattern_profiler.py
pyyacp/profiler/column_stats_profiler.py
pyyacp/profiler/cset_detection.py
pyyacp/profiler/data_type_detection.py
pyyacp/profiler/data_type_interpretation.py
pyyacp/profiler/datatype_interpretation.py
pyyacp/profiler/datetime_context.py
pyyacp/profiler/distributions.py
pyyacp/profiler/empty_cell_detection.py
pyyacp/profiler/fdprofiler.py
pyyacp/profiler/header_readability.py
pyyacp/profiler/outlier.py
pyyacp/profiler/profiling.py
pyyacp/profiler/simple_type_detection.py
pyyacp/profiler/xsd11_type_detection.py
pyyacp/profiler/ideas/__init__.py
pyyacp/profiler/ideas/header_readability.py
pyyacp/profiler/ideas/outlier.py
pyyacp/profiler/ideas/xsd11_type_detection.py
pyyacp/profiler/xsd11/__init__.py
pyyacp/profiler/xsd11/anyatomic_decimal.py
pyyacp/profiler/xsd11/types.py
pyyacp/web/to_html.py
pyyacp/web/static/.gitkeep
pyyacp/web/static/css/csvengine.css
pyyacp/web/static/img/adequate_logo_extended.png
pyyacp/web/static/img/wu.png
pyyacp/web/static/swagger/index.html
pyyacp/web/static/swagger/o2c.html
pyyacp/web/static/swagger/swagger-ui.js
pyyacp/web/static/swagger/swagger-ui.min.js
pyyacp/web/static/swagger/css/print.css
pyyacp/web/static/swagger/css/reset.css
pyyacp/web/static/swagger/css/screen.css
pyyacp/web/static/swagger/css/style.css
pyyacp/web/static/swagger/css/typography.css
pyyacp/web/static/swagger/fonts/DroidSans-Bold.ttf
pyyacp/web/static/swagger/fonts/DroidSans.ttf
pyyacp/web/static/swagger/images/collapse.gif
pyyacp/web/static/swagger/images/expand.gif
pyyacp/web/static/swagger/images/explorer_icons.png
pyyacp/web/static/swagger/images/favicon-16x16.png
pyyacp/web/static/swagger/images/favicon-32x32.png
pyyacp/web/static/swagger/images/favicon.ico
pyyacp/web/static/swagger/images/logo_small.png
pyyacp-0.7.dist-info/METADATA
pyyacp-0.7.dist-info/RECORD
pyyacp-0.7.dist-info/WHEEL
pyyacp-0.7.dist-info/entry_points.txt
pyyacp-0.7.dist-info/top_level.txt
