Metadata-Version: 2.1
Name: pyyacp
Version: 0.7
Summary: Add a short description here!
Home-page: http://...
Author: jumbrich
Author-email: jueumb@gmail.com
License: mit
Platform: any
Classifier: Development Status :: 4 - Beta
Classifier: Programming Language :: Python
Requires-Dist: dtpattern
Requires-Dist: pyanycsv
Requires-Dist: pandas
Requires-Dist: numpy
Requires-Dist: structlog
Requires-Dist: requests
Requires-Dist: cchardet
Requires-Dist: markupsafe
Requires-Dist: pyjuhelpers
Requires-Dist: click
Requires-Dist: jinja2
